qentangle/__init__.py
qentangle/main.py
qentangle-0.0.2.dist-info/LICENSE
qentangle-0.0.2.dist-info/METADATA
qentangle-0.0.2.dist-info/WHEEL
qentangle-0.0.2.dist-info/top_level.txt
qentangle-0.0.2.dist-info/RECORD
