Metadata-Version: 2.2
Name: QENTANGLE
Version: 0.0.2
Summary: QENTANGLE Quantum education library
Home-page: https://github.com/brn378/qentangle
Author: Center for Science Engagement,Barnas Monteith,Anna Du
Author-email: barnas@engagescience.org
Classifier: Programming Language :: Python :: 3
Classifier: License :: OSI Approved :: MIT License
Classifier: Operating System :: OS Independent
License-File: LICENSE
Dynamic: author
Dynamic: author-email
Dynamic: classifier
Dynamic: description
Dynamic: description-content-type
Dynamic: home-page
Dynamic: summary
